blescivis/__init__.py
blescivis-0.1.dist-info/LICENSE
blescivis-0.1.dist-info/METADATA
blescivis-0.1.dist-info/WHEEL
blescivis-0.1.dist-info/top_level.txt
blescivis-0.1.dist-info/RECORD
