Metadata-Version: 2.1
Name: blescivis
Version: 0.1
Summary: A package with tailored functions for scientific visualization in Blender via scripting through Blender's Python API
Home-page: https://github.com/pererossello/blescivis
Author: Pere Rosselló
Author-email: per.rossello@gmail.com
Classifier: Programming Language :: Python :: 3
Classifier: License :: OSI Approved :: MIT License
Classifier: Operating System :: OS Independent
Requires-Python: >=3.11
License-File: LICENSE
Requires-Dist: numpy ==1.24.3
